fake/__init__.py
fake/_version.py
fake/fake.py
python_fake-0.2.0.dist-info/METADATA
python_fake-0.2.0.dist-info/WHEEL
python_fake-0.2.0.dist-info/RECORD
