Metadata-Version: 2.4
Name: python-fake
Version: 0.2.0
Summary: A general purpose mock library for Python
Project-URL: homepage, https://github.com/sassanh/python-fake/
Project-URL: repository, https://github.com/sassanh/python-fake/
Project-URL: documentation, https://github.com/sassanh/python-fake/
Project-URL: changelog, https://github.com/sassanh/python-fake/blob/main/CHANGELOG.md
Author-email: Sassan Haradji <me@sassanh.com>
Maintainer-email: Sassan Haradji <me@sassanh.com>
License: Apache-2.0
Keywords: double,dummy,fake,mock,pytest,python,spy,stub,testing,unittest
Requires-Python: >=3.11
